{
  "author": {
    "id": "t2_ab9xd",
    "name": "cecil-explodes"
  },
  "date": 1502890408,
  "id": "t3_6u0081",
  "misc": {
    "postHint": "image"
  },
  "picture": {
    "full": "https://preview.redd.it/ikf0rv0nd1gz.png?auto=webp&s=cc31f08c6eb33fc92178b54c5e470c2336de1bba",
    "preview": "https://preview.redd.it/ikf0rv0nd1gz.png?width=640&crop=smart&auto=webp&s=c3555c457f9075760a24f53a94dcaf253baddc80",
    "thumbnail": "https://a.thumbs.redditmedia.com/_5VXwj7d_tAv6EihK-K1eaDpkClnEJ7AD--u9qefG60.jpg"
  },
  "score": {
    "comments": 13,
    "downs": 0,
    "isCurated": false,
    "ratio": 0.95,
    "ups": 92,
    "value": 92
  },
  "subreddit": {
    "id": "t5_3isai",
    "name": "dndmaps"
  },
  "tags": [],
  "title": "These two /r/dndmaps thumbnails look like one map",
  "url": "https://www.reddit.com/r/dndmaps/comments/6u0081/these_two_rdndmaps_thumbnails_look_like_one_map/"
}
