{
  "author": {
    "id": "t2_hjdph",
    "name": "DrWabbel"
  },
  "date": {
    "day": 1603929600,
    "full": 1603999282,
    "month": 1601510400,
    "week": 1603584000
  },
  "id": "t3_jkgp2d",
  "misc": {
    "postHint": "image"
  },
  "picture": {
    "full": "https://preview.redd.it/pi67v37n33w51.jpg?auto=webp&s=944505e437786c03ea52b5198eb6e479446f1849",
    "preview": "https://preview.redd.it/pi67v37n33w51.jpg?width=640&crop=smart&auto=webp&s=87e15a468fcb8bece9809cbc341325037d78d59f",
    "thumbnail": "https://b.thumbs.redditmedia.com/-TxyjLL_Hg7bCfN2LtPSS6WFsZU3X7eab0sw8XCWBCI.jpg"
  },
  "score": {
    "comments": 0,
    "downs": 0,
    "isCurated": false,
    "ratio": 1,
    "ups": 6,
    "value": 6
  },
  "subreddit": {
    "id": "t5_3isai",
    "name": "dndmaps"
  },
  "tags": ["Encounter"],
  "title": "Giant mytical tree - Battlemap",
  "url": "https://www.reddit.com/r/dndmaps/comments/jkgp2d/giant_mytical_tree_battlemap/"
}
