{
  "author": {
    "id": "t2_7wfdatdn",
    "name": "sketchforge"
  },
  "date": {
    "day": 1603065600,
    "full": 1603111618,
    "month": 1601510400,
    "week": 1602979200
  },
  "id": "t3_je0zck",
  "misc": {
    "postHint": "image"
  },
  "picture": {
    "full": "https://preview.redd.it/1k021p16s1u51.png?auto=webp&s=010b0d65c1acfc4511016a38bdab5f28ec002339",
    "preview": "https://preview.redd.it/1k021p16s1u51.png?width=640&crop=smart&auto=webp&s=b55869ebc668a3dec13c47a7156b51cf0565107c",
    "thumbnail": "https://b.thumbs.redditmedia.com/JHNn_GF6pkGzy5L0iS9XfXe5aF1--6kOe-NPWoGPKTw.jpg"
  },
  "score": {
    "comments": 1,
    "downs": 0,
    "isCurated": false,
    "ratio": 0.98,
    "ups": 31,
    "value": 31
  },
  "subreddit": {
    "id": "t5_3isai",
    "name": "dndmaps"
  },
  "tags": ["Building"],
  "title": "Inktober: Dizzy",
  "url": "https://www.reddit.com/r/dndmaps/comments/je0zck/inktober_dizzy_25x25/"
}
