{
  "author": {
    "id": "t2_wuitb",
    "name": "GeraltsFirstWish"
  },
  "date": {
    "day": 1610841600,
    "full": 1610912874,
    "month": 1609459200,
    "week": 1610841600
  },
  "id": "t3_kzdfmf",
  "misc": {
    "postHint": "image"
  },
  "picture": {
    "full": "https://preview.redd.it/4xvu1tff5yb61.jpg?auto=webp&s=45277529aadd12cb0d0e6ad620c26e3d942553a9",
    "preview": "https://preview.redd.it/4xvu1tff5yb61.jpg?width=640&crop=smart&auto=webp&s=ab0c8b3b22a4c4090895498ff09795b4f82ec78b",
    "thumbnail": "https://a.thumbs.redditmedia.com/I2a7AjmxHTmofXDaeKaFjq4UN9MIM5Yur2B_YfMQIM8.jpg"
  },
  "score": {
    "comments": 0,
    "downs": 0,
    "isCurated": false,
    "ratio": 0.98,
    "ups": 60,
    "value": 60
  },
  "subreddit": {
    "id": "t5_3isai",
    "name": "dndmaps"
  },
  "tags": ["Dungeon"],
  "title": "Cultist Lair. Complete with secret passage!",
  "url": "https://www.reddit.com/r/dndmaps/comments/kzdfmf/cultist_lair_complete_with_secret_passage/"
}
