{
  "author": {
    "id": "t2_4c3gz8i6",
    "name": "Elderbrain_com"
  },
  "date": {
    "day": 1610582400,
    "full": 1610624485,
    "month": 1609459200,
    "week": 1610236800
  },
  "id": "t3_kx42sy",
  "misc": {
    "postHint": "image"
  },
  "picture": {
    "full": "https://preview.redd.it/gy2y8zfybab61.jpg?auto=webp&s=5b414b1c585378de09079c0f1c654283971efc6e",
    "preview": "https://preview.redd.it/gy2y8zfybab61.jpg?width=640&crop=smart&auto=webp&s=d995e55231060d431cc568a7468713a03a9ead26",
    "thumbnail": "https://b.thumbs.redditmedia.com/ZfT3Xbx3I80gSitN8j_RhBjZkdhFZL2j0YG-w2ef2rU.jpg"
  },
  "score": {
    "comments": 4,
    "downs": 0,
    "isCurated": false,
    "ratio": 1,
    "ups": 13,
    "value": 13
  },
  "subreddit": {
    "id": "t5_3isai",
    "name": "dndmaps"
  },
  "tags": ["Building"],
  "title": "The Eyrie of the Fabled on the Shadowrealm",
  "url": "https://www.reddit.com/r/dndmaps/comments/kx42sy/oc_the_eyrie_of_the_fabled_on_the_shadowrealm/"
}
