{
  "author": {
    "id": "t2_7td0638n",
    "name": "ZMMaps"
  },
  "date": {
    "day": 1609459200,
    "full": 1609533761,
    "month": 1609459200,
    "week": 1609027200
  },
  "id": "t3_koinqa",
  "misc": {
    "postHint": "image"
  },
  "picture": {
    "full": "https://preview.redd.it/cqtnrovn8s861.jpg?auto=webp&s=09a1af4b5226c98e246d7822db6adae700b533b6",
    "preview": "https://preview.redd.it/cqtnrovn8s861.jpg?width=640&crop=smart&auto=webp&s=f9e769676f6462874eb7da2344cd28b5466aa0c1",
    "thumbnail": "https://b.thumbs.redditmedia.com/WdAqEYfbCVo_bT3ho-B9Bou5P7nE6wo1UdHJzJjnJvI.jpg"
  },
  "score": {
    "comments": 1,
    "downs": 0,
    "isCurated": false,
    "ratio": 1,
    "ups": 5,
    "value": 5
  },
  "subreddit": {
    "id": "t5_3isai",
    "name": "dndmaps"
  },
  "tags": ["Encounter"],
  "title": "Wayshrine Crossroad",
  "url": "https://www.reddit.com/r/dndmaps/comments/koinqa/wayshrine_crossroad_25x25oc/"
}
