{
  "author": {
    "id": "t2_4djd3ph8",
    "name": "Sacred_F0x"
  },
  "date": 1567495560,
  "id": "t3_cywsra",
  "misc": {
    "postHint": "image"
  },
  "picture": {
    "full": "https://preview.redd.it/e6hid2vul9k31.jpg?auto=webp&s=9b1fe4ab63be8e6095f0221bc330543ff818b86d",
    "preview": "https://preview.redd.it/e6hid2vul9k31.jpg?width=640&crop=smart&auto=webp&s=8f8c4ab6de1fd07ab4686772520d6869860e10a1",
    "thumbnail": "https://b.thumbs.redditmedia.com/n8ECGYdtWB03g5eYCVg2Q310b1EdaxfPZVnIUzkNLRM.jpg"
  },
  "score": {
    "comments": 16,
    "downs": 0,
    "ratio": 0.99,
    "ups": 469,
    "value": 469
  },
  "subreddit": {
    "id": "t5_3isai",
    "name": "dndmaps"
  },
  "tags": [],
  "title": "Cavern Map With Grid",
  "url": "https://www.reddit.com/r/dndmaps/comments/cywsra/cavern_map_with_grid/"
}
