{
  "author": {
    "id": "t2_1pa83dmr",
    "name": "AfternoonMaps"
  },
  "date": 1535934246,
  "id": "t3_9cdauf",
  "misc": {
    "postHint": "image"
  },
  "picture": {
    "full": "https://preview.redd.it/454dqa0vjuj11.jpg?auto=webp&s=d3d67a4239bf7fe62e58310fe6c62362e6cc003d",
    "preview": "https://preview.redd.it/454dqa0vjuj11.jpg?width=640&crop=smart&auto=webp&s=ea685e4a1734952c029a8e7971f65abf4d6efbc9",
    "thumbnail": "https://b.thumbs.redditmedia.com/eqMlm4i4ky_NtDeHPeXrArduL-OU6Re4xw9SdJC-Kyo.jpg"
  },
  "score": {
    "comments": 13,
    "downs": 0,
    "isCurated": true,
    "ratio": 0.99,
    "ups": 184,
    "value": 184
  },
  "subreddit": {
    "id": "t5_3isai",
    "name": "dndmaps"
  },
  "tags": ["Encounter"],
  "title": "Woodland Den Battle Map",
  "url": "https://www.reddit.com/r/dndmaps/comments/9cdauf/woodland_den_battle_map/"
}
