{
  "author": {
    "id": "t2_jps0u2",
    "name": "Ravenousfire"
  },
  "date": 1585052395,
  "id": "t3_fnyrlq",
  "misc": {
    "postHint": "image"
  },
  "picture": {
    "full": "https://preview.redd.it/4gxtsg6brjo41.jpg?auto=webp&s=b2d9ec445feb62ed8013b41257a4c4b8b5e057bc",
    "preview": "https://preview.redd.it/4gxtsg6brjo41.jpg?width=640&crop=smart&auto=webp&s=7d7517e3b1e68e4a331a7c5fcd96640ad9836b26",
    "thumbnail": "https://b.thumbs.redditmedia.com/PixCkROFKU_F5w9MWplKvsTPZpiHSZ6suLCsrSRjpqQ.jpg"
  },
  "score": {
    "comments": 9,
    "downs": 0,
    "isCurated": false,
    "ratio": 1,
    "ups": 262,
    "value": 262
  },
  "subreddit": {
    "id": "t5_3isai",
    "name": "dndmaps"
  },
  "tags": ["Encounter"],
  "title": "The Crossroads",
  "url": "https://www.reddit.com/r/dndmaps/comments/fnyrlq/the_crossroads_24x24/"
}
