{
  "author": {
    "id": "t2_3r3mt9sj",
    "name": "mapguffin"
  },
  "date": 1585514950,
  "id": "t3_fr5em1",
  "misc": {
    "postHint": "image"
  },
  "picture": {
    "full": "https://preview.redd.it/58mjxjdixlp41.jpg?auto=webp&s=6fc46f4de1fcd7722a456428f87aace8e5b55881",
    "preview": "https://preview.redd.it/58mjxjdixlp41.jpg?width=640&crop=smart&auto=webp&s=bbf36a3574a7a1d448819a5c3cd2fc70cdfbfd5e",
    "thumbnail": "https://b.thumbs.redditmedia.com/SCLTXbsQpXy7-heDn2jDqSWnL1x-Tu1T4OSq59VpBOo.jpg"
  },
  "score": {
    "comments": 1,
    "downs": 0,
    "ratio": 0.97,
    "ups": 81,
    "value": 81
  },
  "subreddit": {
    "id": "t5_3isai",
    "name": "dndmaps"
  },
  "tags": ["Encounter Map"],
  "title": "Diamond Dias 40x22",
  "url": "https://www.reddit.com/r/dndmaps/comments/fr5em1/ocartbattlemapanimatedperspective_diamond_dias/"
}
