{
  "author": {
    "name": "[deleted]"
  },
  "date": {
    "day": 1504224000,
    "full": 1504227043,
    "month": 1504224000,
    "week": 1503792000
  },
  "id": "t3_6xb5n5",
  "misc": {
    "postHint": "image"
  },
  "picture": {
    "full": "https://preview.redd.it/b2f2hwbm56jz.png?auto=webp&s=4fedb2d19b287970b1b1bc3d6da688e9b56a5397",
    "preview": "https://preview.redd.it/b2f2hwbm56jz.png?width=640&crop=smart&auto=webp&s=31711a50245e3d7f4b45e90aed3ab9ab2ff1aad5",
    "thumbnail": "https://b.thumbs.redditmedia.com/3-PWSRoe-1bwZa0DwwXmNuVTT0q5FfxisPSf8d364wI.jpg"
  },
  "score": {
    "comments": 25,
    "downs": 0,
    "isCurated": false,
    "ratio": 0.95,
    "ups": 209,
    "value": 209
  },
  "subreddit": {
    "id": "t5_3isai",
    "name": "dndmaps"
  },
  "tags": ["World"],
  "title": "Brand names often sound like fantasy names, so...",
  "url": "https://www.reddit.com/r/dndmaps/comments/6xb5n5/brand_names_often_sound_like_fantasy_names_so/"
}
