{
  "author": {
    "id": "t2_2d7t3zq2",
    "name": "nightgraydawg"
  },
  "date": {
    "day": 1623542400,
    "full": 1623624595,
    "month": 1622505600,
    "week": 1623542400
  },
  "id": "t3_nz872q",
  "misc": {
    "postHint": "image"
  },
  "picture": {
    "full": "https://preview.redd.it/izmff3nx34571.jpg?auto=webp&s=7096490510e4a7f1d617b175441cf0c70237f328",
    "preview": "https://preview.redd.it/izmff3nx34571.jpg?width=640&crop=smart&auto=webp&s=2929408123cf1a665efaffa89a875222065c5e75",
    "thumbnail": "https://b.thumbs.redditmedia.com/0d2l8Qr-Ab0JW6NwVGAPMBC7xcXlJq6eMoUfmYQt8uA.jpg"
  },
  "score": {
    "comments": 4,
    "downs": 0,
    "isCurated": false,
    "ratio": 0.91,
    "ups": 40,
    "value": 40
  },
  "subreddit": {
    "id": "t5_3isai",
    "name": "dndmaps"
  },
  "tags": ["Region"],
  "title": "The Kingdom of Jourgyall, the setting for my upcoming Viking/zombie adventure",
  "url": "https://www.reddit.com/r/dndmaps/comments/nz872q/the_kingdom_of_jourgyall_the_setting_for_my/"
}
