{
  "author": {
    "id": "t2_18hywuyt",
    "name": "zenir_altis"
  },
  "date": 1549750237,
  "id": "t3_aosmrt",
  "misc": {
    "postHint": "image"
  },
  "picture": {
    "full": "https://preview.redd.it/12awir81vjf21.jpg?auto=webp&s=bf4deba6624c55c058c5325754039fa45f530632",
    "preview": "https://preview.redd.it/12awir81vjf21.jpg?width=640&crop=smart&auto=webp&s=cd153ea8c31d4312b6051b950e833ffeff2f0b5a",
    "thumbnail": "https://a.thumbs.redditmedia.com/uY-KagabaSfzpr_eJPLjCDYkWBpziEdbHacjTTMM4Y8.jpg"
  },
  "score": {
    "comments": 6,
    "downs": 0,
    "isCurated": false,
    "ratio": 0.89,
    "ups": 7,
    "value": 7
  },
  "subreddit": {
    "id": "t5_3isai",
    "name": "dndmaps"
  },
  "tags": ["World"],
  "title": "I made a Map for Dnd. First try at cartography so advice is more than welcome. Credits to someone I don't remember name of (^_^;)...sorry",
  "url": "https://www.reddit.com/r/dndmaps/comments/aosmrt/i_made_a_map_for_dnd_first_try_at_cartography_so/"
}
