{
  "author": {
    "id": "t2_z6s4z",
    "name": "derekvonzarovich"
  },
  "date": 1489107434,
  "id": "t3_5yg74p",
  "misc": {
    "postHint": "link"
  },
  "picture": {
    "full": "https://external-preview.redd.it/whM-nlmlkcDhma_VM3cnhGxSAeSkl1t7fSNAvPnofnA.jpg?auto=webp&s=a67a3ad0982271f28550c796908989b75992f07e",
    "preview": "https://external-preview.redd.it/whM-nlmlkcDhma_VM3cnhGxSAeSkl1t7fSNAvPnofnA.jpg?width=640&crop=smart&auto=webp&s=e295a724706b089cdcb5a477dd37435ed954e58b",
    "thumbnail": "https://b.thumbs.redditmedia.com/Spigmc_Z9og67RC0WxLv87juiDTuflpxkiel5zZBHSY.jpg"
  },
  "score": {
    "comments": 1,
    "downs": 0,
    "ratio": 0.91,
    "ups": 39,
    "value": 39
  },
  "subreddit": {
    "id": "t5_3isai",
    "name": "dndmaps"
  },
  "tags": ["Cave"],
  "title": "New cave map !",
  "url": "https://www.reddit.com/r/dndmaps/comments/5yg74p/new_cave_map/"
}
