{
  "author": {
    "id": "t2_3c9z46g4",
    "name": "GoAdventureMapsEx"
  },
  "date": 1566418038,
  "id": "t3_ctfwyr",
  "misc": {
    "postHint": "image"
  },
  "picture": {
    "full": "https://preview.redd.it/aj1nbh2vlsh31.jpg?auto=webp&s=8675280b095ca1acbff41dded7c78d719138bf00",
    "preview": "https://preview.redd.it/aj1nbh2vlsh31.jpg?width=640&crop=smart&auto=webp&s=5b87210bff9ee1a6f7094e77b2aa0305bf785003",
    "thumbnail": "https://a.thumbs.redditmedia.com/eh1KqsDA3IqMHsKz3kRtg1_XvKwQwzssYK1xZn0zyq0.jpg"
  },
  "score": {
    "comments": 1,
    "downs": 0,
    "isCurated": true,
    "ratio": 0.98,
    "ups": 107,
    "value": 107
  },
  "subreddit": {
    "id": "t5_3isai",
    "name": "dndmaps"
  },
  "tags": ["Encounter"],
  "title": "Sea Cave",
  "url": "https://www.reddit.com/r/dndmaps/comments/ctfwyr/ocart_sea_cave/"
}
