{
  "author": {
    "id": "t2_1s1ehtu2",
    "name": "Corgeti"
  },
  "date": 1555046643,
  "id": "t3_bc5dkd",
  "misc": {
    "postHint": "image"
  },
  "picture": {
    "full": "https://preview.redd.it/741jqy8gcpr21.jpg?auto=webp&s=bbd7662e6bbbd0657744409d7a5e43eef3ccceb5",
    "preview": "https://preview.redd.it/741jqy8gcpr21.jpg?width=640&crop=smart&auto=webp&s=4bf439b3051260b888eb5eb74e5956c260492268",
    "thumbnail": "https://b.thumbs.redditmedia.com/fWhfJ0U8kKNnU7u1zzU690FlICjA7MniEhdEaK16W9E.jpg"
  },
  "score": {
    "comments": 1,
    "downs": 0,
    "isCurated": false,
    "ratio": 1,
    "ups": 15,
    "value": 15
  },
  "subreddit": {
    "id": "t5_3isai",
    "name": "dndmaps"
  },
  "tags": ["Building"],
  "title": "Envil's Archive",
  "url": "https://www.reddit.com/r/dndmaps/comments/bc5dkd/envils_archive/"
}
