{
  "author": {
    "id": "t2_edefg3m",
    "name": "Kyrgioan"
  },
  "date": 1558203507,
  "id": "t3_bq2in1",
  "misc": {
    "postHint": "image"
  },
  "picture": {
    "full": "https://preview.redd.it/z07064vq3yy21.png?auto=webp&s=58547271f6bea53dea08ff76d6f60d6f36d910a1",
    "preview": "https://preview.redd.it/z07064vq3yy21.png?width=640&crop=smart&auto=webp&s=69d5956b49f588e65190effdcc27bb91ac6df411",
    "thumbnail": "https://b.thumbs.redditmedia.com/frLpPyAx4hxbldbb4fjOTzvq_Zf6HOTwk9m3POQB5iQ.jpg"
  },
  "score": {
    "comments": 51,
    "downs": 0,
    "ratio": 0.99,
    "ups": 976,
    "value": 976
  },
  "subreddit": {
    "id": "t5_3isai",
    "name": "dndmaps"
  },
  "tags": [],
  "title": "My DM'S epic creation. Edareen",
  "url": "https://www.reddit.com/r/dndmaps/comments/bq2in1/my_dms_epic_creation_edareen/"
}
