{
  "author": {
    "id": "t2_2razpjnz",
    "name": "_PogS_"
  },
  "date": 1591402067,
  "id": "t3_gx7eyi",
  "misc": {
    "postHint": "image"
  },
  "picture": {
    "full": "https://preview.redd.it/ura14y5r74351.jpg?auto=webp&s=5e723e43ff26483f511c940d30a4ab8660ce1ab1",
    "preview": "https://preview.redd.it/ura14y5r74351.jpg?width=640&crop=smart&auto=webp&s=467689aa3e69bfcd974093db83c72d3a24577557",
    "thumbnail": "https://a.thumbs.redditmedia.com/snaYI8IPjWiNycQJIRDFlxYOLn5E0LzydY7tQsjbqn4.jpg"
  },
  "score": {
    "comments": 1,
    "downs": 0,
    "ratio": 0.96,
    "ups": 61,
    "value": 61
  },
  "subreddit": {
    "id": "t5_3isai",
    "name": "dndmaps"
  },
  "tags": ["Building"],
  "title": "High Hall",
  "url": "https://www.reddit.com/r/dndmaps/comments/gx7eyi/high_hall/"
}
