{
  "author": {
    "id": "t2_64ujt8mh",
    "name": "7empests"
  },
  "date": {
    "day": 1620000000,
    "full": 1620059571,
    "month": 1619827200,
    "week": 1619913600
  },
  "id": "t3_n40kd0",
  "misc": {
    "postHint": "image"
  },
  "picture": {
    "full": "https://preview.redd.it/0ul8lb03nxw61.jpg?auto=webp&s=bea7405111bb8cc6da5cb53fec5f97711ceb3eb3",
    "preview": "https://preview.redd.it/0ul8lb03nxw61.jpg?width=640&crop=smart&auto=webp&s=797a31cc7e20b3684c6452314163c7a014ba134d",
    "thumbnail": "https://b.thumbs.redditmedia.com/ME6_VQKdUgmJzuZdE6ZEIrUXXK8rvcukDdvuio2oPtY.jpg"
  },
  "score": {
    "comments": 1,
    "downs": 0,
    "isCurated": false,
    "ratio": 0.93,
    "ups": 18,
    "value": 18
  },
  "subreddit": {
    "id": "t5_3isai",
    "name": "dndmaps"
  },
  "tags": [],
  "title": "Here is Tenant, the Capital of Tenatra. Watercolor city",
  "url": "https://www.reddit.com/r/dndmaps/comments/n40kd0/here_is_tenant_the_capital_of_tenatra_watercolor/"
}
