{
  "author": {
    "id": "t2_lzs6o",
    "name": "mrvalor"
  },
  "date": 1565338746,
  "id": "t3_cnuhua",
  "misc": {
    "postHint": "link"
  },
  "picture": {
    "full": "https://external-preview.redd.it/YhhI_VH5k-3dJZq2E0QGLkaNZcjYXbG9dIPhNShUm40.jpg?auto=webp&s=5f17810a2716a4e8f98806b899bac85d3eba829e",
    "preview": "https://external-preview.redd.it/YhhI_VH5k-3dJZq2E0QGLkaNZcjYXbG9dIPhNShUm40.jpg?width=640&crop=smart&auto=webp&s=44f7ff3130cab3410af39af309e1e9bd6c95dbca",
    "thumbnail": "https://b.thumbs.redditmedia.com/u7L7DbQAOYQqvA3r0b0H7ifQPlIKq8ajAdKdDHcFbmc.jpg"
  },
  "score": {
    "comments": 1,
    "downs": 0,
    "isCurated": false,
    "ratio": 0.81,
    "ups": 9,
    "value": 9
  },
  "subreddit": {
    "id": "t5_3isai",
    "name": "dndmaps"
  },
  "tags": [],
  "title": "4 Free 50x50 Town Street Dock Maps w/ day & night versions (made of 25x25 modular tiles). Info in comments.",
  "url": "https://www.reddit.com/r/dndmaps/comments/cnuhua/4_free_50x50_town_street_dock_maps_w_day_night/"
}
