{
  "author": {
    "id": "t2_4ie2smfu",
    "name": "EightfoldPaper"
  },
  "date": 1580072728,
  "id": "t3_eu6gnu",
  "misc": {
    "postHint": "image"
  },
  "picture": {
    "full": "https://preview.redd.it/ei0n3g09g4d41.jpg?auto=webp&s=e11274a5ae53633462e4db39e34d7c1a97e9be79",
    "preview": "https://preview.redd.it/ei0n3g09g4d41.jpg?width=640&crop=smart&auto=webp&s=8b380ca515374cb79dcd570dd6f99596026e6d62",
    "thumbnail": "https://b.thumbs.redditmedia.com/jbTxWBk6WVFwumNOhEpAsvCMEnvam9TS9LN4bfh0pSM.jpg"
  },
  "score": {
    "comments": 32,
    "downs": 0,
    "ratio": 1,
    "ups": 1995,
    "value": 1995
  },
  "subreddit": {
    "id": "t5_3isai",
    "name": "dndmaps"
  },
  "tags": ["Dungeon"],
  "title": "The Forgotten Ruins of Nine Eyes [Part 3] [19x25]",
  "url": "https://www.reddit.com/r/dndmaps/comments/eu6gnu/the_forgotten_ruins_of_nine_eyes_part_3_19x25/"
}
