{
  "author": {
    "id": "t2_m7yvx",
    "name": "Icarus_Miniatures"
  },
  "date": 1582951281,
  "id": "t3_fb18li",
  "misc": {},
  "picture": {
    "full": "https://youtu.be/Pspx23RIzuY",
    "preview": false,
    "thumbnail": "default"
  },
  "score": {
    "comments": 1,
    "downs": 0,
    "ratio": 0.62,
    "ups": 2,
    "value": 2
  },
  "subreddit": {
    "id": "t5_3isai",
    "name": "dndmaps"
  },
  "tags": ["Dungeon"],
  "title": "Dungeondraft Map Maker Overview &amp; Review",
  "url": "https://www.reddit.com/r/dndmaps/comments/fb18li/dungeondraft_map_maker_overview_review/"
}
