{
  "author": {
    "name": "[deleted]"
  },
  "date": {
    "day": 1578528000,
    "full": 1578607897,
    "month": 1577836800,
    "week": 1578182400
  },
  "id": "t3_emgxb0",
  "misc": {
    "postHint": "image"
  },
  "picture": {
    "full": "https://preview.redd.it/9d38fwtgtt941.png?auto=webp&s=9a1e8e553ce7f019f3b5abe0d9bdb12f02c4caa6",
    "preview": "https://preview.redd.it/9d38fwtgtt941.png?width=640&crop=smart&auto=webp&s=70edc4926bde76e847fca81a512067965ad7a28d",
    "thumbnail": "https://a.thumbs.redditmedia.com/yCch0878-H6G_bWj9MWw3dOTR668FxiNE_beovYXG98.jpg"
  },
  "score": {
    "comments": 2,
    "downs": 0,
    "isCurated": false,
    "ratio": 1,
    "ups": 15,
    "value": 15
  },
  "subreddit": {
    "id": "t5_3isai",
    "name": "dndmaps"
  },
  "tags": ["Encounter"],
  "title": "Desert Railway Station Battle Map I did - Link in Comments",
  "url": "https://www.reddit.com/r/dndmaps/comments/emgxb0/desert_railway_station_battle_map_i_did_link_in/"
}
