{
  "author": {
    "id": "t2_he8wq",
    "name": "Vezuvian"
  },
  "date": {
    "day": 1607040000,
    "full": 1607083125,
    "month": 1606780800,
    "week": 1606608000
  },
  "id": "t3_k6jllv",
  "misc": {
    "postHint": "link"
  },
  "picture": {
    "full": "https://external-preview.redd.it/KD9O9PPPX_Z-37cijKYrtKKIUwjR7alVY4h3VvBiSL4.jpg?auto=webp&s=2ac2e463a54b7027911e2d5a03500171091c44cf",
    "preview": "https://external-preview.redd.it/KD9O9PPPX_Z-37cijKYrtKKIUwjR7alVY4h3VvBiSL4.jpg?width=640&crop=smart&auto=webp&s=2671c217634a0aa615c771bec1817ff3167e010d",
    "thumbnail": "https://b.thumbs.redditmedia.com/ZAviC6MESMOmHAcICJO-w4-_sR7URff2oF1Sluke23g.jpg"
  },
  "score": {
    "comments": 0,
    "downs": 0,
    "isCurated": false,
    "ratio": 1,
    "ups": 1,
    "value": 1
  },
  "subreddit": {
    "id": "t5_3isai",
    "name": "dndmaps"
  },
  "tags": [],
  "title": "My first city map using Watabu and Wonderdraft: Daamarc, the capital of the Tikeroc Concord. I'm not sure how to shrink the file size to post to imgur.",
  "url": "https://www.reddit.com/r/dndmaps/comments/k6jllv/my_first_city_map_using_watabu_and_wonderdraft/"
}
