{
  "author": {
    "id": "t2_4zyso1sq",
    "name": "TheModernLich"
  },
  "date": {
    "day": 1609286400,
    "full": 1609346704,
    "month": 1606780800,
    "week": 1609027200
  },
  "id": "t3_kn5nnx",
  "misc": {
    "postHint": "image"
  },
  "picture": {
    "full": "https://preview.redd.it/4505liefsc861.jpg?auto=webp&s=08e2cfd6c37306b93ce31889a2b94842d79bb13b",
    "preview": "https://preview.redd.it/4505liefsc861.jpg?width=640&crop=smart&auto=webp&s=970cece9b12b929c38ba88db9014bdbd8a17fbc3",
    "thumbnail": "https://b.thumbs.redditmedia.com/lF_xDgK4fMw4HDbCBWNFxpByTOfnbTqSw_wzu2KiSwM.jpg"
  },
  "score": {
    "comments": 1,
    "downs": 0,
    "isCurated": false,
    "ratio": 0.97,
    "ups": 50,
    "value": 50
  },
  "subreddit": {
    "id": "t5_3isai",
    "name": "dndmaps"
  },
  "tags": ["Encounter"],
  "title": "Cave Entrance",
  "url": "https://www.reddit.com/r/dndmaps/comments/kn5nnx/cave_entrance_35x35battlemapoc/"
}
