{
  "author": {
    "id": "t2_4dpmnx26",
    "name": "Iorica"
  },
  "date": {
    "day": 1607731200,
    "full": 1607812856,
    "month": 1606780800,
    "week": 1607212800
  },
  "id": "t3_kbyof2",
  "misc": {
    "postHint": "image"
  },
  "picture": {
    "full": "https://preview.redd.it/r3mrmfc1ro461.jpg?auto=webp&s=23fb5feac5a2ef3e696b928dbbe4fdd63f12f937",
    "preview": "https://preview.redd.it/r3mrmfc1ro461.jpg?width=640&crop=smart&auto=webp&s=afba2a5fd7bcd5978d647ca50b9def38a6d68896",
    "thumbnail": "https://b.thumbs.redditmedia.com/c_hmwwrIsik13gxFwE-hZ3C1pOKJVKv1VHZQDtTQuew.jpg"
  },
  "score": {
    "comments": 0,
    "downs": 0,
    "isCurated": false,
    "ratio": 0.84,
    "ups": 4,
    "value": 4
  },
  "subreddit": {
    "id": "t5_3isai",
    "name": "dndmaps"
  },
  "tags": [],
  "title": "Agatho's Rest - a small village dedicated to my very first DnD group",
  "url": "https://www.reddit.com/r/dndmaps/comments/kbyof2/agathos_rest_a_small_village_dedicated_to_my_very/"
}
