{
  "author": {
    "id": "t2_dvbw7",
    "name": "LeLanglacier"
  },
  "date": 1559285076,
  "id": "t3_buznfr",
  "misc": {
    "postHint": "image"
  },
  "picture": {
    "full": "https://preview.redd.it/o4h0w9a6df131.jpg?auto=webp&s=954bb7f8f718622303fd40a2e3b8ed9d8c9caa0b",
    "preview": "https://preview.redd.it/o4h0w9a6df131.jpg?width=640&crop=smart&auto=webp&s=142fc3092c5a8432d726a759c121764dac4695d5",
    "thumbnail": "https://b.thumbs.redditmedia.com/yL9oOF0l430c9fOABmKiJdmHdoRvgozpdjHfyFViPtE.jpg"
  },
  "score": {
    "comments": 0,
    "downs": 0,
    "ratio": 0.92,
    "ups": 10,
    "value": 10
  },
  "subreddit": {
    "id": "t5_3isai",
    "name": "dndmaps"
  },
  "tags": [],
  "title": "Small Scene/Map i created for a Boss fight for my party",
  "url": "https://www.reddit.com/r/dndmaps/comments/buznfr/oc_small_scenemap_i_created_for_a_boss_fight_for/"
}
