{
  "author": {
    "id": "t2_2y71bbrt",
    "name": "PabloXDark"
  },
  "date": 1558044338,
  "id": "t3_bpcytg",
  "misc": {
    "postHint": "image"
  },
  "picture": {
    "full": "https://preview.redd.it/eg7h1jlkyky21.jpg?auto=webp&s=0c676346c7754ba7ed296f049a3ea98073f672f8",
    "preview": "https://preview.redd.it/eg7h1jlkyky21.jpg?width=640&crop=smart&auto=webp&s=ffce975d4b45e29cc9db6584a82c41bb5119d32e",
    "thumbnail": "https://b.thumbs.redditmedia.com/9W5LbFCbln1IQ_0Jw_syNur22U4GCapNBJw6Ufd1w5E.jpg"
  },
  "score": {
    "comments": 4,
    "downs": 0,
    "ratio": 1,
    "ups": 10,
    "value": 10
  },
  "subreddit": {
    "id": "t5_3isai",
    "name": "dndmaps"
  },
  "tags": ["Region"],
  "title": "My first Fantasy Map. Now I only need a name for the region/kingdom...",
  "url": "https://www.reddit.com/r/dndmaps/comments/bpcytg/my_first_fantasy_map_now_i_only_need_a_name_for/"
}
