{
  "author": {
    "id": "t2_yv1v2",
    "name": "Eivill"
  },
  "date": 1538911647,
  "id": "t3_9m26bq",
  "misc": {
    "postHint": "image"
  },
  "picture": {
    "full": "https://external-preview.redd.it/bWf1AkaESsc538y5b1Ex1N8U5_ACWprB5dwyShG4IXg.jpg?auto=webp&s=7f62c8504002e8df52755b6f9c6cb64c9828813e",
    "preview": "https://external-preview.redd.it/bWf1AkaESsc538y5b1Ex1N8U5_ACWprB5dwyShG4IXg.jpg?width=640&crop=smart&auto=webp&s=e57d8e4980bab8201178ca348348e074438650ce",
    "thumbnail": "https://b.thumbs.redditmedia.com/VRHym2JpHuzfZx2ege5TxNRcX4TLhxgEigOdRjQHg9U.jpg"
  },
  "score": {
    "comments": 17,
    "downs": 0,
    "isCurated": false,
    "ratio": 0.98,
    "ups": 138,
    "value": 138
  },
  "subreddit": {
    "id": "t5_3isai",
    "name": "dndmaps"
  },
  "tags": [],
  "title": "The Sunken Halls of Odros",
  "url": "https://www.reddit.com/r/dndmaps/comments/9m26bq/the_sunken_halls_of_odros/"
}
