{
  "author": {
    "id": "t2_3cg6bz6g",
    "name": "mitch2187"
  },
  "date": 1570672079,
  "id": "t3_dfkm44",
  "misc": {
    "postHint": "image"
  },
  "picture": {
    "full": "https://preview.redd.it/wusrjmjczjr31.jpg?auto=webp&s=d8b5b1950e1841d6a3afb7aaf9df64602aff7c00",
    "preview": "https://preview.redd.it/wusrjmjczjr31.jpg?width=640&crop=smart&auto=webp&s=6558f3d75dde432f4bf36eec75394caffa592fe3",
    "thumbnail": "https://b.thumbs.redditmedia.com/jVzkNEaTp3vBupbEp5TSWxVzyUmIHscLrA90gG8k-Bw.jpg"
  },
  "score": {
    "comments": 0,
    "downs": 0,
    "ratio": 0.92,
    "ups": 31,
    "value": 31
  },
  "subreddit": {
    "id": "t5_3isai",
    "name": "dndmaps"
  },
  "tags": [],
  "title": "The Kingdom of Calavash, entire world created from scratch for u/whisperinwind87",
  "url": "https://www.reddit.com/r/dndmaps/comments/dfkm44/the_kingdom_of_calavash_entire_world_created_from/"
}
