{
  "author": {
    "id": "t2_4eg5n",
    "name": "KillbotJosiah"
  },
  "date": {
    "day": 1518739200,
    "full": 1518810460,
    "month": 1517443200,
    "week": 1518307200
  },
  "id": "t3_7y1d8x",
  "misc": {
    "postHint": "image"
  },
  "picture": {
    "full": "https://preview.redd.it/fr6kt46npmg01.png?auto=webp&s=5857f4cea4161687ca20234afb63fb85cf48f753",
    "preview": "https://preview.redd.it/fr6kt46npmg01.png?width=640&crop=smart&auto=webp&s=3f044f3bba04419d0f0d10c34fb240bee6d12de3",
    "thumbnail": "https://a.thumbs.redditmedia.com/ySxlNmTdhEqJx1WlXfSspPlBga9VPv4Jq1MOi8qmeZ0.jpg"
  },
  "score": {
    "comments": 7,
    "downs": 0,
    "isCurated": false,
    "ratio": 0.99,
    "ups": 171,
    "value": 171
  },
  "subreddit": {
    "id": "t5_3isai",
    "name": "dndmaps"
  },
  "tags": ["City"],
  "title": "The City of Twin Docks",
  "url": "https://www.reddit.com/r/dndmaps/comments/7y1d8x/the_city_of_twin_docks/"
}
