{
  "author": {
    "id": "t2_ekuth",
    "name": "holding_gold"
  },
  "date": {
    "day": 1614211200,
    "full": 1614279501,
    "month": 1612137600,
    "week": 1613865600
  },
  "id": "t3_lsdyjv",
  "misc": {
    "postHint": "image"
  },
  "picture": {
    "full": "https://preview.redd.it/rtpjoa408oj61.png?auto=webp&s=032ac144d7bb4cefb975b049c872beb0e087238f",
    "preview": "https://preview.redd.it/rtpjoa408oj61.png?width=640&crop=smart&auto=webp&s=0bc07d9b97ac82ae605e15ea49a95b5e97c18d97",
    "thumbnail": "https://b.thumbs.redditmedia.com/HbLyrF2sYHjfZnA64FhLYm5RrjhgqQdx-6Yxpkz5r0g.jpg"
  },
  "score": {
    "comments": 12,
    "downs": 0,
    "isCurated": false,
    "ratio": 0.94,
    "ups": 49,
    "value": 49
  },
  "subreddit": {
    "id": "t5_3isai",
    "name": "dndmaps"
  },
  "tags": ["Dungeon"],
  "title": "Forge of Fury - The Mountain Door",
  "url": "https://www.reddit.com/r/dndmaps/comments/lsdyjv/forge_of_fury_the_mountain_door/"
}
