{
  "author": {
    "id": "t2_22qkgccz",
    "name": "mattecoo"
  },
  "date": 1555652672,
  "id": "t3_ber5sl",
  "misc": {
    "postHint": "image"
  },
  "picture": {
    "full": "https://preview.redd.it/hodq39x6c3t21.jpg?auto=webp&s=2e2ffc0e2dcd05fec81f7625a8bd0c8ff000fc13",
    "preview": "https://preview.redd.it/hodq39x6c3t21.jpg?width=640&crop=smart&auto=webp&s=0ad7d35fb0055fabcd9d51f6a1623b7c04938f8f",
    "thumbnail": "https://b.thumbs.redditmedia.com/kvzwvQobFLbSzsV0QKKo5vBk1CeaUMHFV8NvDYIx66E.jpg"
  },
  "score": {
    "comments": 4,
    "downs": 0,
    "ratio": 0.9,
    "ups": 20,
    "value": 20
  },
  "subreddit": {
    "id": "t5_3isai",
    "name": "dndmaps"
  },
  "tags": ["Region"],
  "title": "[OC]Name the Swamp Settlement",
  "url": "https://www.reddit.com/r/dndmaps/comments/ber5sl/ocname_the_swamp_settlement/"
}
