{
  "author": {
    "id": "t2_6pdej",
    "name": "thealphahobo"
  },
  "date": 1556605865,
  "id": "t3_bivpcu",
  "misc": {
    "postHint": "image"
  },
  "picture": {
    "full": "https://preview.redd.it/g2tq8d095av21.jpg?auto=webp&s=f17326cd2c9bf23df3506209e680c4d414b42086",
    "preview": "https://preview.redd.it/g2tq8d095av21.jpg?width=640&crop=smart&auto=webp&s=67f1fa8b89fbedf1b5a61aa54b93929141e6a4c3",
    "thumbnail": "https://b.thumbs.redditmedia.com/d7oGLo2ebnmH8o-S-OZDTGw4uPZKTQ6GZMPWGu3zGeg.jpg"
  },
  "score": {
    "comments": 4,
    "downs": 0,
    "isCurated": false,
    "ratio": 0.92,
    "ups": 19,
    "value": 19
  },
  "subreddit": {
    "id": "t5_3isai",
    "name": "dndmaps"
  },
  "tags": [],
  "title": "My First Dnd Map, the City of Argyle! Made in Iknarnate",
  "url": "https://www.reddit.com/r/dndmaps/comments/bivpcu/my_first_dnd_map_the_city_of_argyle_made_in/"
}
