{
  "author": {
    "id": "t2_fi70ohl",
    "name": "MattMilby"
  },
  "date": 1554934829,
  "id": "t3_bbml3b",
  "misc": {
    "postHint": "image"
  },
  "picture": {
    "full": "https://preview.redd.it/y24wywkgzfr21.jpg?auto=webp&s=fc6e998e09e5805e47ac0e4e274645de90578a09",
    "preview": "https://preview.redd.it/y24wywkgzfr21.jpg?width=640&crop=smart&auto=webp&s=6f1e5cb2fc0ffc72aef649b648da31a816ddf06b",
    "thumbnail": "https://b.thumbs.redditmedia.com/dVI8bYFRAEBqr6WefF2dY7E72qCrXR3X0nTlgaIe-Qg.jpg"
  },
  "score": {
    "comments": 71,
    "downs": 0,
    "isCurated": false,
    "ratio": 0.99,
    "ups": 1624,
    "value": 1624
  },
  "subreddit": {
    "id": "t5_3isai",
    "name": "dndmaps"
  },
  "tags": ["Building"],
  "title": "I made a map of Neuschwanstein in Bavaria, the most famous of the Mad King Ludwig's castles. Drawn directly from floor plans and photos.",
  "url": "https://www.reddit.com/r/dndmaps/comments/bbml3b/i_made_a_map_of_neuschwanstein_in_bavaria_the/"
}
