{
  "author": {
    "id": "t2_53n7o1mc",
    "name": "phillb123"
  },
  "date": 1588264558,
  "id": "t3_garwks",
  "misc": {
    "postHint": "image"
  },
  "picture": {
    "full": "https://preview.redd.it/g0vwvp2s2xv41.png?auto=webp&s=89494dc1bc6da6e1157d18b51f89b83c872dcf9c",
    "preview": "https://preview.redd.it/g0vwvp2s2xv41.png?width=640&crop=smart&auto=webp&s=a826a24e1af016dd3cd1ec0ac8124cb93e5173d5",
    "thumbnail": "https://a.thumbs.redditmedia.com/BH80Hp5MGD8gpDKLbHJYYHkMkojJr_U6RVyoR--jl04.jpg"
  },
  "score": {
    "comments": 1,
    "downs": 0,
    "ratio": 0.86,
    "ups": 5,
    "value": 5
  },
  "subreddit": {
    "id": "t5_3isai",
    "name": "dndmaps"
  },
  "tags": ["Region"],
  "title": "Brasreim, my homebrew campaign setting",
  "url": "https://www.reddit.com/r/dndmaps/comments/garwks/brasreim_my_homebrew_campaign_setting/"
}
