{
  "author": {
    "id": "t2_532h7mb0",
    "name": "Worldbvilder"
  },
  "date": {
    "day": 1585872000,
    "full": 1585957670,
    "month": 1585699200,
    "week": 1585440000
  },
  "id": "t3_fujace",
  "misc": {
    "postHint": "image"
  },
  "picture": {
    "full": "https://preview.redd.it/2zfbo8gowoq41.jpg?auto=webp&s=6ec2b479b91c098142a92ea00ec8275273f7b2c2",
    "preview": "https://preview.redd.it/2zfbo8gowoq41.jpg?width=640&crop=smart&auto=webp&s=8fef850c0298a127f3826995ce3bf8f079670f27",
    "thumbnail": "https://b.thumbs.redditmedia.com/1tR0rD3cqvfSvxNjp7TMX6o-TeachWf02omfL2n_Psw.jpg"
  },
  "score": {
    "comments": 77,
    "downs": 0,
    "isCurated": false,
    "ratio": 0.99,
    "ups": 1263,
    "value": 1263
  },
  "subreddit": {
    "id": "t5_3isai",
    "name": "dndmaps"
  },
  "tags": ["World"],
  "title": "The Everweald, an Inkarnate world map (6K)",
  "url": "https://www.reddit.com/r/dndmaps/comments/fujace/the_everweald_an_inkarnate_world_map_6k/"
}
