{
  "author": {
    "id": "t2_4yy8u",
    "name": "SimpleRy"
  },
  "date": {
    "day": 1604448000,
    "full": 1604518115,
    "month": 1604188800,
    "week": 1604188800
  },
  "id": "t3_jo363l",
  "misc": {
    "postHint": "image"
  },
  "picture": {
    "full": "https://preview.redd.it/4audvkknx9x51.jpg?auto=webp&s=607962686a325d4166d8d1d2c866a8e4b51ddd6f",
    "preview": "https://preview.redd.it/4audvkknx9x51.jpg?width=640&crop=smart&auto=webp&s=03aa19fa0ce0ac7f3a2150a59f1486433fac7493",
    "thumbnail": "https://b.thumbs.redditmedia.com/9NrBL730aRu3vF2kTgC3YoYNByjtDT-N2MBRm9HnSUI.jpg"
  },
  "score": {
    "comments": 2,
    "downs": 0,
    "isCurated": false,
    "ratio": 1,
    "ups": 31,
    "value": 31
  },
  "subreddit": {
    "id": "t5_3isai",
    "name": "dndmaps"
  },
  "tags": ["Encounter"],
  "title": "Windmill Farm from Vermintide",
  "url": "https://www.reddit.com/r/dndmaps/comments/jo363l/windmill_farm_from_vermintide/"
}
