{
  "author": {
    "id": "t2_5du03an2",
    "name": "the_mad_cartographer"
  },
  "date": {
    "day": 1605744000,
    "full": 1605799884,
    "month": 1604188800,
    "week": 1605398400
  },
  "id": "t3_jx4ram",
  "misc": {
    "postHint": "image"
  },
  "picture": {
    "full": "https://preview.redd.it/1s42t10st7061.jpg?auto=webp&s=df95e4e115d4f419d4702cdb9bb03094adb72675",
    "preview": "https://preview.redd.it/1s42t10st7061.jpg?width=640&crop=smart&auto=webp&s=2be06a7c16d84699b6c16e96c77d9c5644a79ea7",
    "thumbnail": "https://b.thumbs.redditmedia.com/9g0JgYoxtcSxUqUjVGfE1-ee7nYLT0-0oY2k9nMIuUE.jpg"
  },
  "score": {
    "comments": 3,
    "downs": 0,
    "isCurated": false,
    "ratio": 0.97,
    "ups": 24,
    "value": 24
  },
  "subreddit": {
    "id": "t5_3isai",
    "name": "dndmaps"
  },
  "tags": ["Encounter"],
  "title": "Icewind Dale: Knucklehead Trout Fishing",
  "url": "https://www.reddit.com/r/dndmaps/comments/jx4ram/icewind_dale_knucklehead_trout_fishing/"
}
