{
  "author": {
    "id": "t2_bmboi",
    "name": "Centumviri"
  },
  "date": 1497676843,
  "id": "t3_6hpgf3",
  "misc": {
    "postHint": "image"
  },
  "picture": {
    "full": "https://preview.redd.it/73pb95h0r24z.jpg?auto=webp&s=24366e812cf9afbfde48118aa397455f22813a2e",
    "preview": "https://preview.redd.it/73pb95h0r24z.jpg?width=640&crop=smart&auto=webp&s=694ecb5ae76f134d2d11791be7006a40930e0c33",
    "thumbnail": "https://b.thumbs.redditmedia.com/yWvrGYr0DM-Jf4kTK133_rGcNPjRJM1m0xLIqYEiZlY.jpg"
  },
  "score": {
    "comments": 9,
    "downs": 0,
    "isCurated": false,
    "ratio": 1,
    "ups": 64,
    "value": 64
  },
  "subreddit": {
    "id": "t5_3isai",
    "name": "dndmaps"
  },
  "tags": [],
  "title": "The Village of Northwood",
  "url": "https://www.reddit.com/r/dndmaps/comments/6hpgf3/the_village_of_northwood/"
}
