{
  "author": {
    "id": "t2_z35twlh",
    "name": "Katarail"
  },
  "date": 1585843983,
  "id": "t3_ftiibu",
  "misc": {
    "postHint": "image"
  },
  "picture": {
    "full": "https://preview.redd.it/zyiz1uw05dq41.png?auto=webp&s=6b56bbdac42a8916043a6df0cd35f90a316bb9be",
    "preview": "https://preview.redd.it/zyiz1uw05dq41.png?width=640&crop=smart&auto=webp&s=3cb9cf67b20cf7aefdacce11d4995b782f4cbc5a",
    "thumbnail": "https://b.thumbs.redditmedia.com/B4fYzZJezNBrT0FTH7vvaCgdwpyXrDNlqUtNi6ZaUds.jpg"
  },
  "score": {
    "comments": 22,
    "downs": 0,
    "ratio": 0.99,
    "ups": 669,
    "value": 669
  },
  "subreddit": {
    "id": "t5_3isai",
    "name": "dndmaps"
  },
  "tags": [],
  "title": "The region of the Sea of Fire, where is located my campaign (made with Wonderdraft ; sorry for the french version)",
  "url": "https://www.reddit.com/r/dndmaps/comments/ftiibu/the_region_of_the_sea_of_fire_where_is_located_my/"
}
