{
  "author": {
    "id": "t2_6g21untd",
    "name": "celticdungeons"
  },
  "date": {
    "day": 1591142400,
    "full": 1591205385,
    "month": 1590969600,
    "week": 1590883200
  },
  "id": "t3_gvyaop",
  "misc": {
    "postHint": "image"
  },
  "picture": {
    "full": "https://preview.redd.it/qbhcsxv4cq251.png?auto=webp&s=3172d24f08a806b214555f765d9d569630e08b0b",
    "preview": "https://preview.redd.it/qbhcsxv4cq251.png?width=640&crop=smart&auto=webp&s=e61e4f6c875dd5c2d8c3c080ebb6b5493aa2cd7c",
    "thumbnail": "https://b.thumbs.redditmedia.com/w36ftVRVy811FK12paGypRxUdsvelySTxbpwSOyzpNI.jpg"
  },
  "score": {
    "comments": 1,
    "downs": 0,
    "isCurated": true,
    "ratio": 0.97,
    "ups": 73,
    "value": 73
  },
  "subreddit": {
    "id": "t5_3isai",
    "name": "dndmaps"
  },
  "tags": ["Encounter"],
  "title": "DunJune 03 - The Spider's Web",
  "url": "https://www.reddit.com/r/dndmaps/comments/gvyaop/dunjune_03_the_spiders_web/"
}
