{
  "author": {
    "id": "t2_2t74rvfj",
    "name": "dotheminimum"
  },
  "date": 1551277288,
  "id": "t3_ava5ma",
  "misc": {
    "postHint": "image"
  },
  "picture": {
    "full": "https://preview.redd.it/1v51ttpb02j21.png?auto=webp&s=a76c5c8026e599e0f26063e0d823bb3052f155f8",
    "preview": "https://preview.redd.it/1v51ttpb02j21.png?width=640&crop=smart&auto=webp&s=b7eb73c1f382af7a6a001144d93de1384b74291b",
    "thumbnail": "https://a.thumbs.redditmedia.com/p90rIr00XkYsKrFYL_iAFJQ4pE7pZrTEa9Y2VPgmZ74.jpg"
  },
  "score": {
    "comments": 3,
    "downs": 0,
    "ratio": 0.97,
    "ups": 36,
    "value": 36
  },
  "subreddit": {
    "id": "t5_3isai",
    "name": "dndmaps"
  },
  "tags": ["Building Map"],
  "title": "Old Sanctuary",
  "url": "https://www.reddit.com/r/dndmaps/comments/ava5ma/old_sanctuary/"
}
