{
  "author": {
    "id": "t2_3s7wa7pu",
    "name": "Wertopter"
  },
  "date": 1559903774,
  "id": "t3_bxpdrh",
  "misc": {
    "postHint": "image"
  },
  "picture": {
    "full": "https://preview.redd.it/o3o08azhju231.jpg?auto=webp&s=2d77750a3709f62d5122500da8b08e41071b8225",
    "preview": "https://preview.redd.it/o3o08azhju231.jpg?width=640&crop=smart&auto=webp&s=291262c81e57b2e5079c4960be8cca3eb112338e",
    "thumbnail": "https://a.thumbs.redditmedia.com/Y_OYrbhdA2oWiVsynY3PAas38O8cmL8EJoi5H_p6RU0.jpg"
  },
  "score": {
    "comments": 1,
    "downs": 0,
    "ratio": 0.7,
    "ups": 5,
    "value": 5
  },
  "subreddit": {
    "id": "t5_3isai",
    "name": "dndmaps"
  },
  "tags": ["World"],
  "title": "Xolvier",
  "url": "https://www.reddit.com/r/dndmaps/comments/bxpdrh/xolvier/"
}
