{
  "author": {
    "id": "t2_15wa3v",
    "name": "ScalpelArts"
  },
  "date": 1559939914,
  "id": "t3_bxu4eo",
  "misc": {
    "postHint": "image"
  },
  "picture": {
    "full": "https://preview.redd.it/12l0w1u0jx231.png?auto=webp&s=a4a2f2bd8cd62f0df17ebe54f6740b43064f102d",
    "preview": "https://preview.redd.it/12l0w1u0jx231.png?width=640&crop=smart&auto=webp&s=bf962a1a4c0ebf05d39465136e59728f831802ee",
    "thumbnail": "https://b.thumbs.redditmedia.com/9MLfN0YwFeM-mj9awT3jWpqkIGpBsOl2W9AILNn4lec.jpg"
  },
  "score": {
    "comments": 9,
    "downs": 0,
    "ratio": 0.99,
    "ups": 616,
    "value": 616
  },
  "subreddit": {
    "id": "t5_3isai",
    "name": "dndmaps"
  },
  "tags": ["Encounter"],
  "title": "Island Battle Map 42x42",
  "url": "https://www.reddit.com/r/dndmaps/comments/bxu4eo/island_battle_map_42x42/"
}
