{
  "author": {
    "id": "t2_3flrb4ea",
    "name": "patreoncomDnDavid"
  },
  "date": {
    "day": 1615161600,
    "full": 1615177592,
    "month": 1614556800,
    "week": 1615075200
  },
  "id": "t3_m07qcd",
  "misc": {
    "postHint": "image"
  },
  "picture": {
    "full": "https://preview.redd.it/e982yqtpeql61.jpg?auto=webp&s=a8afaa821323966f257e84ef33a3ff1eb63b398d",
    "preview": "https://preview.redd.it/e982yqtpeql61.jpg?width=640&crop=smart&auto=webp&s=299b8960f3e8f0d8862b09e962ca41570a200b8f",
    "thumbnail": "https://b.thumbs.redditmedia.com/ZI3r-z74LSkBJ0NZReAnGPpxAsVicVJ4ZUQzgO2kFog.jpg"
  },
  "score": {
    "comments": 1,
    "downs": 0,
    "isCurated": false,
    "ratio": 0.9,
    "ups": 40,
    "value": 40
  },
  "subreddit": {
    "id": "t5_3isai",
    "name": "dndmaps"
  },
  "tags": [],
  "title": "Tea with the Bamboo Sage",
  "url": "https://www.reddit.com/r/dndmaps/comments/m07qcd/tea_with_the_bamboo_sage_30x40/"
}
