{
  "author": {
    "id": "t2_8roni551",
    "name": "The_Berge"
  },
  "date": {
    "day": 1616889600,
    "full": 1616922706,
    "month": 1614556800,
    "week": 1616889600
  },
  "id": "t3_mexzmf",
  "misc": {
    "postHint": "image"
  },
  "picture": {
    "full": "https://preview.redd.it/ibxhzmfsjqp61.jpg?auto=webp&s=509521746d7779d55662e9b98ef9ed8de36a45f2",
    "preview": "https://preview.redd.it/ibxhzmfsjqp61.jpg?width=640&crop=smart&auto=webp&s=0fb51d7c06cd4e1c1a194c04b9d062c127757b82",
    "thumbnail": "https://b.thumbs.redditmedia.com/qZT2unZXaLxn6eQ2l09aZ98zltiB2dc7yjJ6tbALa6c.jpg"
  },
  "score": {
    "comments": 7,
    "downs": 0,
    "isCurated": false,
    "ratio": 1,
    "ups": 153,
    "value": 153
  },
  "subreddit": {
    "id": "t5_3isai",
    "name": "dndmaps"
  },
  "tags": ["Encounter"],
  "title": "Snowy Mead Hall",
  "url": "https://www.reddit.com/r/dndmaps/comments/mexzmf/snowy_mead_hall/"
}
