{
  "author": {
    "id": "t2_2gq2vohs",
    "name": "Tavern_Tales"
  },
  "date": 1575668227,
  "id": "t3_e6yumo",
  "misc": {
    "postHint": "image"
  },
  "picture": {
    "full": "https://preview.redd.it/59u6amten0341.jpg?auto=webp&s=b4d8e82e77adb9ccf0143f56b9d271d7ec0cb69c",
    "preview": "https://preview.redd.it/59u6amten0341.jpg?width=640&crop=smart&auto=webp&s=81058a0482d127a2a5f5e60f7144a9fc9d4c7519",
    "thumbnail": "https://b.thumbs.redditmedia.com/c3Gqaxp-_AoLTy_X4TeCSG_NqCzb6SUQZKkHWBjpwvg.jpg"
  },
  "score": {
    "comments": 1,
    "downs": 0,
    "ratio": 1,
    "ups": 30,
    "value": 30
  },
  "subreddit": {
    "id": "t5_3isai",
    "name": "dndmaps"
  },
  "tags": [],
  "title": "Aqueduct [25x20]",
  "url": "https://www.reddit.com/r/dndmaps/comments/e6yumo/aqueduct_25x20/"
}
