{
  "author": {
    "id": "t2_17bqxq",
    "name": "Hjanzo"
  },
  "date": 1506843640,
  "id": "t3_73icq9",
  "misc": {
    "postHint": "link"
  },
  "picture": {
    "full": "https://external-preview.redd.it/Rnh9eQZgllsfXYpHmLNc-LHrG-CWIQkjCd_FKfIdUpM.jpg?auto=webp&s=a239a8bd7a7bf5d84340db528cb15445b99da6dc",
    "preview": "https://external-preview.redd.it/Rnh9eQZgllsfXYpHmLNc-LHrG-CWIQkjCd_FKfIdUpM.jpg?width=640&crop=smart&auto=webp&s=9dc221c598ea2f4110ddf58a2e1bc5dc5a91b04e",
    "thumbnail": "https://b.thumbs.redditmedia.com/A4AGAFGxrfhG071ZMcMZao2hO-x7RA5yXsHyhC7Sn7g.jpg"
  },
  "score": {
    "comments": 0,
    "downs": 0,
    "ratio": 0.9,
    "ups": 14,
    "value": 14
  },
  "subreddit": {
    "id": "t5_3isai",
    "name": "dndmaps"
  },
  "tags": [],
  "title": "Titanfell",
  "url": "https://www.reddit.com/r/dndmaps/comments/73icq9/titanfell/"
}
