{
  "author": {
    "id": "t2_6j62vk0v",
    "name": "StormforgedMaps"
  },
  "date": 1590183906,
  "id": "t3_gojm50",
  "misc": {
    "postHint": "image"
  },
  "picture": {
    "full": "https://preview.redd.it/07gdt2k9lb051.png?auto=webp&s=2695f6a2f2eab042b8bfe3d64c0f80f117b63891",
    "preview": "https://preview.redd.it/07gdt2k9lb051.png?width=640&crop=smart&auto=webp&s=172d10f24f8cfc56c07c8fe5d4da9e67f8a02815",
    "thumbnail": "https://b.thumbs.redditmedia.com/_a2dZ_Zli7uTKAq9wWrnDnydgqY9BiFldvyPQWLEmKI.jpg"
  },
  "score": {
    "comments": 1,
    "downs": 0,
    "ratio": 0.99,
    "ups": 44,
    "value": 44
  },
  "subreddit": {
    "id": "t5_3isai",
    "name": "dndmaps"
  },
  "tags": ["Encounter"],
  "title": "Roadside Ruins [14x21]",
  "url": "https://www.reddit.com/r/dndmaps/comments/gojm50/roadside_ruins_14x21/"
}
