{
  "author": {
    "id": "t2_16u79vku",
    "name": "Omniisabii"
  },
  "date": 1584254507,
  "id": "t3_fir1er",
  "misc": {
    "postHint": "image"
  },
  "picture": {
    "full": "https://preview.redd.it/2cz1winvupm41.jpg?auto=webp&s=55ae9743bbdea75edde9cadaa89e2f40e3247ef1",
    "preview": "https://preview.redd.it/2cz1winvupm41.jpg?width=640&crop=smart&auto=webp&s=d909d5dfe00a47dbb2cd92659abf94eb0b71d150",
    "thumbnail": "https://a.thumbs.redditmedia.com/hu2xcndl0G0kn4iKQ665XKnrWLqCAIOg1Kx4TcGL6D8.jpg"
  },
  "score": {
    "comments": 0,
    "downs": 0,
    "ratio": 0.92,
    "ups": 16,
    "value": 16
  },
  "subreddit": {
    "id": "t5_3isai",
    "name": "dndmaps"
  },
  "tags": [],
  "title": "Orcs and humans of Goldheart.",
  "url": "https://www.reddit.com/r/dndmaps/comments/fir1er/orcs_and_humans_of_goldheart/"
}
