{
  "author": {
    "id": "t2_69y1q7",
    "name": "JaccarTheProgrammer"
  },
  "date": 1530227538,
  "id": "t3_8ukbbk",
  "misc": {
    "postHint": "image"
  },
  "picture": {
    "full": "https://preview.redd.it/e4je3fmb4r611.jpg?auto=webp&s=6432656ce9b67dd21d21c506c161ce727d3d631b",
    "preview": "https://preview.redd.it/e4je3fmb4r611.jpg?width=640&crop=smart&auto=webp&s=a566a3998a0340d392e1322c6a6328c1fe231822",
    "thumbnail": "https://b.thumbs.redditmedia.com/x3LV9nYBe-zC93zbe0K3woJG4jsJfl2zT4miwpMyEUg.jpg"
  },
  "score": {
    "comments": 7,
    "downs": 0,
    "ratio": 0.96,
    "ups": 49,
    "value": 49
  },
  "subreddit": {
    "id": "t5_3isai",
    "name": "dndmaps"
  },
  "tags": ["Region"],
  "title": "Updated: The Talotian Hegemony - colored",
  "url": "https://www.reddit.com/r/dndmaps/comments/8ukbbk/updated_the_talotian_hegemony_colored/"
}
